README
setup.py
scripts/pywatch
src/pywatch/__init__.py
src/pywatch/autotest.py
src/pywatch/tests.py
src/pywatch/watcher.py
src/pywatch.egg-info/PKG-INFO
src/pywatch.egg-info/SOURCES.txt
src/pywatch.egg-info/dependency_links.txt
src/pywatch.egg-info/requires.txt
src/pywatch.egg-info/top_level.txt