Metadata-Version: 1.0
Name: pywatch
Version: 0.3.1
Summary: Runs arbitrary commands if files specified to be watched change.
Home-page: http://heisel.org/blog/code/pywatch/
Author: Chris Heisel
Author-email: chris@heisel.org
License: MIT
Platform: UNKNOWN
Classifier: Development Status :: 4 - Beta
Classifier: Environment :: Console
Classifier: Intended Audience :: Developers
Classifier: License :: OSI Approved :: MIT License
Classifier: Natural Language :: English
Classifier: Programming Language :: Python
Classifier: Topic :: Software Development :: Libraries :: Python Modules
